rx_common/utilities.py
rx_common-0.0.6.data/scripts/rx_setup
rx_common_scripts/ap_lfn_to_yaml.py
rx_common_scripts/make_run3_yaml.py
rx_common_scripts/pap_lfn_to_yaml.py
rx_common_scripts/rx_setup
rx_config/sample_run12.yaml
rx_config/sample_run3.yaml
rx_kernel/__init__.py
rx_kernel/allowed_conf.py
rx_kernel/config_holder.py
rx_kernel/event_type.py
rx_kernel/test_utilities.py
rx_kernel/tuple_holder.py
rx_kernel/tuple_reader.py
rx_kernel/yaml_cutreader.py
rx_tests/kernel/yaml_cutreader.yaml
rx_common-0.0.6.dist-info/METADATA
rx_common-0.0.6.dist-info/WHEEL
rx_common-0.0.6.dist-info/entry_points.txt
rx_common-0.0.6.dist-info/top_level.txt
rx_common-0.0.6.dist-info/RECORD
