Metadata-Version: 2.4
Name: rx_common
Version: 0.0.6
Summary: Project used to find and load libraries in cal-rx-run3 c++ code
Requires-Dist: data-manipulation-utilities
Requires-Dist: PyYAML
Requires-Dist: ap_utilities
Requires-Dist: rx_data
Requires-Dist: post_ap
Provides-Extra: dev
Requires-Dist: pytest; extra == "dev"
